pysh/__init__.py
pysh/config.py
pysh/codec/__init__.py
pysh/codec/excepts.py
pysh/codec/parser.py
pysh/codec/parser2.py
pysh/codec/register.py
pysh/codec/token.py
pysh/codec/tokenizer.py
pysh/lib/FakeFile.py
pysh/lib/__init__.py
pysh/lib/exec.py
pysh/lib/filter.py
pysh/lib/generate_param.py
pysh/lib/pack_name.py
pysh/lib/switch.py
pysh/lib/template.py
tmp/build-env-4xhgvmwr/lib/python3.10/site-packages/pysh.pth
pysh_run-1.1.dist-info/METADATA
pysh_run-1.1.dist-info/WHEEL
pysh_run-1.1.dist-info/top_level.txt
pysh_run-1.1.dist-info/RECORD
