Metadata-Version: 2.1
Name: pysh-run
Version: 1.1
Summary: Run program like bash scripts.
Home-page: https://github.com/w-mj/Pysh
Author: w-mj && lolydleo
Author-email: wmj@alphamj.cn
License: MIT
Keywords: run program bash
Classifier: Intended Audience :: Developers
Classifier: License :: OSI Approved :: MIT License
Classifier: Operating System :: OS Independent
Classifier: Programming Language :: Python
Classifier: Programming Language :: Python :: 3
Classifier: Topic :: Software Development :: Libraries :: Python Modules
